kagent/adk/__init__.py
kagent/adk/_a2a.py
kagent/adk/_agent_executor.py
kagent/adk/_lifespan.py
kagent/adk/_session_service.py
kagent/adk/_token.py
kagent/adk/cli.py
kagent/adk/sandbox_code_executer.py
kagent/adk/skill_fetcher.py
kagent/adk/types.py
kagent/adk/artifacts/__init__.py
kagent/adk/artifacts/artifacts_toolset.py
kagent/adk/artifacts/return_artifacts_tool.py
kagent/adk/artifacts/session_path.py
kagent/adk/artifacts/stage_artifacts_tool.py
kagent/adk/converters/__init__.py
kagent/adk/converters/error_mappings.py
kagent/adk/converters/event_converter.py
kagent/adk/converters/part_converter.py
kagent/adk/converters/request_converter.py
kagent/adk/models/__init__.py
kagent/adk/models/_openai.py
kagent/adk/models/_ssl.py
kagent/adk/skills/README.md
kagent/adk/skills/__init__.py
kagent/adk/skills/skill_tool.py
kagent/adk/skills/skills_plugin.py
kagent/adk/skills/skills_toolset.py
kagent/adk/tools/__init__.py
kagent/adk/tools/bash_tool.py
kagent/adk/tools/file_tools.py
kagent_adk-0.7.8.dist-info/METADATA
kagent_adk-0.7.8.dist-info/WHEEL
kagent_adk-0.7.8.dist-info/entry_points.txt
kagent_adk-0.7.8.dist-info/RECORD
